{
    "metaDataVersion": "1.0.0",
    "category": "com.microchip.ide.project",
    "content": {
        "metaDataVersion": "1.3.0",
        "name": "com.microchip.mcu8.mplabx.project.pic-tcpip-lite-encx24j600-solution",
        "version": "1.0.0",
        "displayName": "ENCx24J600 TCPIP Solutions with PIC",
        "projectName": "pic-tcpip-lite-encx24j600-solution",
        "shortDescription": "This MPLAB® X MCC example shows implementation of TCP/IP Lite Applications using Microchip ENCx24J600 Ethernet Driver on a PIC Device",
        "ide": {
            "name": "MPLAB X",
            "semverRange": "^6.10.0"
        },
        "compiler": [
            {
                "name": "XC8",
                "semverRange": "^2.41.0"
            }
        ],
        "dfp": {
            "name": "PIC16F1xxxx_DFP",
            "semverRange": "^1.17.343"
        },
        "configurator": {
            "name": "MCC",
            "semverRange": "^5.3.7"
        },
        "device": {
            "metaDataVersion": "1.0.0",
            "category": "com.microchip.portal.contentRef",
            "content": {
                "metaDataVersion": "1.0.0",
                "category": "com.microchip.device",
                "name": "PIC16F18857",
                "versionRange": "*"
            }
        },
        "author": "Microchip",
        "peripherals": [
            "Interrupt",
            "SPI",
            "TMR"
        ],
        "keywords": [
            "MCC",
            "MCC Melody",
            "TCP/IP",
            "Ethernet",
            "Curiosity",
            "Curiosity Nano",
            "UDP",
            "TCP"
        ],
        "additionalData": {
            "longDescription": {
                "metaDataVersion": "1.0.0",
                "category": "com.microchip.portal.fileRef",
                "content": {
                    "metaDataVersion": "1.0.0",
                    "fileName": "./README.md",
                    "mimeType": "text/markdown"
                }
            }
        }
    }
}